cafplot/__init__.py
cafplot/plot/__init__.py
cafplot/plot/funcs.py
cafplot/plot/nphist.py
cafplot/plot/ratio.py
cafplot/plot/rhist.py
cafplot/plot/surface.py
cafplot/rfile/__init__.py
cafplot/rfile/funcs.py
cafplot/rfile/irfile.py
cafplot/rfile/json_rfile.py
cafplot/rfile/root_file.py
cafplot/rhist/__init__.py
cafplot/rhist/rhist.py
cafplot/rhist/rhist1d.py
cafplot/rhist/rhist2d.py
cafplot/spectrum/__init__.py
cafplot/spectrum/spectrum.py
cafplot/stats/__init__.py
cafplot/stats/hist.py
cafplot/stats/stats.py
cafplot/surface/__init__.py
cafplot/surface/fsurface.py
cafplot/surface/surface.py
cafplot-0.1.dist-info/LICENSE
cafplot-0.1.dist-info/METADATA
cafplot-0.1.dist-info/WHEEL
cafplot-0.1.dist-info/top_level.txt
cafplot-0.1.dist-info/RECORD
