Metadata-Version: 2.1
Name: cafplot
Version: 0.1
Summary: Library to plot CAFAna objects in python/matplotlib
Home-page: https://github.com/usert5432/cafplot
Author: Dmitrii Torbunov
Author-email: torbu001@umn.edu
License: MIT
Platform: UNKNOWN
Classifier: License :: OSI Approved :: MIT License
Classifier: Programming Language :: Python :: 3 :: Only
Requires-Dist: numpy
Requires-Dist: matplotlib
Requires-Dist: scipy
